{
  "fetched_at": "2026-06-17T15:04:59.754197+00:00",
  "source": "https://theanalyst.com/competition/fifa-world-cup/predictions",
  "probabilities": {
    "France": 0.1563,
    "Argentina": 0.1265,
    "Spain": 0.12210000000000001,
    "England": 0.0981,
    "Portugal": 0.0755,
    "Germany": 0.0691,
    "Brazil": 0.0537,
    "Norway": 0.0482,
    "Netherlands": 0.0322,
    "United States": 0.026699999999999998,
    "Colombia": 0.0202,
    "Belgium": 0.0194,
    "Morocco": 0.0165,
    "Mexico": 0.0152,
    "Japan": 0.013000000000000001,
    "Croatia": 0.013000000000000001,
    "Uruguay": 0.011200000000000002,
    "Sweden": 0.0101,
    "Switzerland": 0.01,
    "Australia": 0.0084,
    "Korea Republic": 0.006999999999999999,
    "Ecuador": 0.0069,
    "Austria": 0.005600000000000001,
    "Senegal": 0.004699999999999999,
    "Canada": 0.0042,
    "C\u00f4te d'Ivoire": 0.0038,
    "Egypt": 0.0036,
    "Scotland": 0.0029,
    "T\u00fcrkiye": 0.0024,
    "Bosnia-Herzegovina": 0.0021,
    "Ghana": 0.0016,
    "Algeria": 0.0016,
    "Czechia": 0.0014000000000000002,
    "IR Iran": 0.0012,
    "Congo DR": 0.001,
    "Paraguay": 0.0009,
    "Panama": 0.0007000000000000001,
    "Saudi Arabia": 0.0006,
    "Cabo Verde": 0.0006,
    "Qatar": 0.0005,
    "Uzbekistan": 0.0005,
    "New Zealand": 0.0004,
    "South Africa": 0.0002,
    "Iraq": 0.0001,
    "Tunisia": 0.0001,
    "Jordan": 0.0001,
    "Haiti": 0.0,
    "Cura\u00e7ao": 0.0
  },
  "model_updated_at": "2026-06-17T08:10:59Z"
}